ibapi/__init__.py
ibapi/account_summary_tags.py
ibapi/client.py
ibapi/client_utils.py
ibapi/comm.py
ibapi/commission_and_fees_report.py
ibapi/common.py
ibapi/connection.py
ibapi/const.py
ibapi/contract.py
ibapi/decoder.py
ibapi/decoder_utils.py
ibapi/enum_implem.py
ibapi/errors.py
ibapi/execution.py
ibapi/ineligibility_reason.py
ibapi/message.py
ibapi/news.py
ibapi/object_implem.py
ibapi/order.py
ibapi/order_cancel.py
ibapi/order_condition.py
ibapi/order_state.py
ibapi/orderdecoder.py
ibapi/reader.py
ibapi/scanner.py
ibapi/server_versions.py
ibapi/softdollartier.py
ibapi/tag_value.py
ibapi/ticktype.py
ibapi/utils.py
ibapi/wrapper.py
ibapi/protobuf/CancelOrderRequest_pb2.py
ibapi/protobuf/ComboLeg_pb2.py
ibapi/protobuf/Contract_pb2.py
ibapi/protobuf/DeltaNeutralContract_pb2.py
ibapi/protobuf/ErrorMessage_pb2.py
ibapi/protobuf/ExecutionDetailsEnd_pb2.py
ibapi/protobuf/ExecutionDetails_pb2.py
ibapi/protobuf/ExecutionFilter_pb2.py
ibapi/protobuf/ExecutionRequest_pb2.py
ibapi/protobuf/Execution_pb2.py
ibapi/protobuf/GlobalCancelRequest_pb2.py
ibapi/protobuf/OpenOrder_pb2.py
ibapi/protobuf/OpenOrdersEnd_pb2.py
ibapi/protobuf/OrderAllocation_pb2.py
ibapi/protobuf/OrderCancel_pb2.py
ibapi/protobuf/OrderCondition_pb2.py
ibapi/protobuf/OrderState_pb2.py
ibapi/protobuf/OrderStatus_pb2.py
ibapi/protobuf/Order_pb2.py
ibapi/protobuf/PlaceOrderRequest_pb2.py
ibapi/protobuf/SoftDollarTier_pb2.py
ibapi_stable-10.37.2.dist-info/METADATA
ibapi_stable-10.37.2.dist-info/WHEEL
ibapi_stable-10.37.2.dist-info/top_level.txt
ibapi_stable-10.37.2.dist-info/RECORD
